meow/__init__.py
meow/meow.py
meow_md-0.3.0.dist-info/licenses/LICENSE
meow_md-0.3.0.dist-info/METADATA
meow_md-0.3.0.dist-info/WHEEL
meow_md-0.3.0.dist-info/entry_points.txt
meow_md-0.3.0.dist-info/top_level.txt
meow_md-0.3.0.dist-info/RECORD
