Metadata-Version: 2.4
Name: meow-md
Version: 0.3.0
Summary: Markdown renderer with Rich
Author-email: sailorfe <sailorf@proton.me>
License-Expression: MIT
Project-URL: Repository, https://codeberg.org/sailorfe/meow
Keywords: markdown,cat
Classifier: Development Status :: 4 - Beta
Classifier: Programming Language :: Python :: 3
Classifier: Programming Language :: Python :: 3.13
Requires-Python: <=4.0,>=3.8
License-File: LICENSE
Requires-Dist: rich>=13.0
Requires-Dist: pygments>=2.16
Requires-Dist: markdown-it-py>=3.0
Dynamic: license-file
